.coveragerc
LICENSE
MANIFEST.in
README.rst
requirements.txt
setup.py
test-requirements.txt
tox.ini
micropath/__init__.py
micropath/controller.py
micropath/elements.py
micropath/injector.py
micropath/request.py
micropath.egg-info/PKG-INFO
micropath.egg-info/SOURCES.txt
micropath.egg-info/dependency_links.txt
micropath.egg-info/requires.txt
micropath.egg-info/top_level.txt
tests/__init__.py
tests/function/__init__.py
tests/function/test_simple.py
tests/function/utils.py
tests/unit/__init__.py
tests/unit/test_controller.py
tests/unit/test_elements.py
tests/unit/test_injector.py
tests/unit/test_request.py